build_cub/__init__.py
build_cub/__main__.py
build_cub/hooks.py
build_cub/plugins.py
build_cub/py.typed
build_cub/_internal/__init__.py
build_cub/_internal/_cmds.py
build_cub/_internal/_version.pyi
build_cub/_internal/cli.py
build_cub/_internal/debug.py
build_cub/_internal/info.py
build_cub/models/__init__.py
build_cub/models/_backends.py
build_cub/models/_base.py
build_cub/models/_build_data.py
build_cub/models/_defaults.py
build_cub/models/_misc.py
build_cub/models/_templates.py
build_cub/models/_version.py
build_cub/utils/__init__.py
build_cub/utils/_classes.py
build_cub/utils/_config.py
build_cub/utils/_exec.py
build_cub/utils/_funcs.py
build_cub/utils/_ignore_handler.py
build_cub/utils/_printer.py
build_cub/utils/_raw_config.py
build_cub/utils/_strings.py
build_cub/utils/_toml_file.py
build_cub/utils/_types.py
build_cub/validation/__init__.py
build_cub/validation/_backends.py
build_cub/validation/_base.py
build_cub/validation/_constants.py
build_cub/validation/_helpers.py
build_cub/validation/_models.py
build_cub/validation/_templates.py
build_cub/workers/__init__.py
build_cub/workers/_base_worker.py
build_cub/workers/_meta.py
build_cub/workers/backends/__init__.py
build_cub/workers/backends/_base.py
build_cub/workers/backends/_cpp_base.py
build_cub/workers/backends/cython.py
build_cub/workers/backends/pybind11.py
build_cub/workers/backends/pyo3.py
build_cub/workers/backends/raw_cpp.py
build_cub/workers/plugins/__init__.py
build_cub/workers/plugins/gperf.py
build_cub-0.0.17.dist-info/METADATA
build_cub-0.0.17.dist-info/WHEEL
build_cub-0.0.17.dist-info/entry_points.txt
build_cub-0.0.17.dist-info/RECORD
