Metadata-Version: 2.4
Name: build-cub
Version: 0.0.17
Summary: A dynamic versioning, Cython, PyBind11, and Raw C API building. Experimental.
Author-email: chaz <bright.lid5647@fastmail.com>
Requires-Python: >=3.12
Requires-Dist: bear-config>=1.0.6
Requires-Dist: dunamai>=1.25.0
Requires-Dist: hatchling>=1.28.0
Requires-Dist: jinja2>=3.1.6
Requires-Dist: lazy-bear>=0.0.6
Requires-Dist: pathspec>=1.0.3
Requires-Dist: pydantic>=2.12.5
Requires-Dist: rich>=14.2.0
Requires-Dist: setuptools>=80.10.1
Requires-Dist: singleton-base>=1.2.4
